junifer_data/__init__.py
junifer_data/__init__.pyi
junifer_data/_cli.py
junifer_data/_functions.py
junifer_data/_utils.py
junifer_data/_version.py
junifer_data/py.typed
junifer_data-1.3.0.dist-info/licenses/LICENSE
junifer_data-1.3.0.dist-info/METADATA
junifer_data-1.3.0.dist-info/WHEEL
junifer_data-1.3.0.dist-info/entry_points.txt
junifer_data-1.3.0.dist-info/top_level.txt
junifer_data-1.3.0.dist-info/RECORD
