Metadata-Version: 2.4
Name: junifer_data
Version: 1.3.0
Summary: Python client for junifer-data
Author-email: Synchon Mandal <s.mandal@fz-juelich.de>
Maintainer-email: Synchon Mandal <s.mandal@fz-juelich.de>
License: AGPL-3.0-only
Project-URL: Source, https://github.com/juaml/junifer-data-client
Classifier: Development Status :: 4 - Beta
Classifier: Intended Audience :: Developers
Classifier: Intended Audience :: Science/Research
Classifier: License :: OSI Approved
Classifier: Natural Language :: English
Classifier: Operating System :: OS Independent
Classifier: Programming Language :: Python :: 3.9
Classifier: Programming Language :: Python :: 3.10
Classifier: Programming Language :: Python :: 3.11
Classifier: Programming Language :: Python :: 3.12
Classifier: Programming Language :: Python :: 3.13
Classifier: Topic :: Software Development
Classifier: Topic :: Scientific/Engineering
Classifier: Topic :: Scientific/Engineering :: Bio-Informatics
Classifier: Topic :: Utilities
Requires-Python: >=3.9
License-File: LICENSE
Requires-Dist: click<8.2,>=8.1.3
Requires-Dist: datalad<1.2.0,>=1.0.0
Requires-Dist: lazy_loader==0.4
Provides-Extra: dev
Requires-Dist: tox; extra == "dev"
Requires-Dist: pre-commit; extra == "dev"
Requires-Dist: ruff; extra == "dev"
Requires-Dist: towncrier; extra == "dev"
Dynamic: license-file
